tests/__init__.py
tests/test.py
tr34_sdk/__init__.py
tr34_sdk/main.py
tr34_sdk/exceptions/__init__.py
tr34_sdk/exceptions/main.py
tr34_sdk/types/__init__.py
tr34_sdk/types/post.py
tr34_sdk/types/tags.py
tr34_sdk-0.1.0.dev1.dist-info/LICENSE.txt
tr34_sdk-0.1.0.dev1.dist-info/METADATA
tr34_sdk-0.1.0.dev1.dist-info/WHEEL
tr34_sdk-0.1.0.dev1.dist-info/top_level.txt
tr34_sdk-0.1.0.dev1.dist-info/RECORD
