Metadata-Version: 2.1
Name: tr34-sdk
Version: 0.1.0.dev1
Summary: Asynchronous sdk for top-rule34 api
Author: StarMan12
Author-email: StarMan12 <author@example.com>
Project-URL: Homepage, https://github.com/SyperAlexKomp/tr34-sdk
Project-URL: Bug Tracker, https://github.com/SyperAlexKomp/tr34-sdk/issues
Classifier: Programming Language :: Python :: 3
Classifier: License :: OSI Approved :: MIT License
Classifier: Operating System :: OS Independent
Requires-Python: >=3.9
License-File: LICENSE.txt
Requires-Dist: aiohttp
Requires-Dist: pydantic ~=2.6.4
